registerrecordobject/__init__.py
registerrecordobject/registerasync.py
registerrecordobject/registersync.py
registerrecordobject-0.0.2.dist-info/METADATA
registerrecordobject-0.0.2.dist-info/WHEEL
registerrecordobject-0.0.2.dist-info/top_level.txt
registerrecordobject-0.0.2.dist-info/RECORD
