Metadata-Version: 2.1
Name: registerrecordobject
Version: 0.0.2
Summary: Register Record Object
Home-page: UNKNOWN
Author: Nico Wolyniec
Author-email: nawolyniec@teys.es
License: MIT
Platform: UNKNOWN
Requires-Python: >=3.8
Requires-Dist: aiohttp
Requires-Dist: requests (>=2.31)
